httpie_jwt_auth.py
httpie_jwt_auth-0.4.0.dist-info/AUTHORS.md
httpie_jwt_auth-0.4.0.dist-info/LICENSE
httpie_jwt_auth-0.4.0.dist-info/METADATA
httpie_jwt_auth-0.4.0.dist-info/WHEEL
httpie_jwt_auth-0.4.0.dist-info/entry_points.txt
httpie_jwt_auth-0.4.0.dist-info/top_level.txt
httpie_jwt_auth-0.4.0.dist-info/RECORD
