Metadata-Version: 2.1
Name: httpie-jwt-auth
Version: 0.4.0
Summary: JWTAuth plugin for HTTPie.
Home-page: https://github.com/teracyhq/httpie-jwt-auth
Author: hoatle
Author-email: hoatle@teracy.com
License: BSD
Download-URL: https://github.com/teracyhq/httpie-jwt-auth
Platform: UNKNOWN
Classifier: Development Status :: 4 - Beta
Classifier: Programming Language :: Python
Classifier: Programming Language :: Python :: 2
Classifier: Programming Language :: Python :: 2.7
Classifier: Programming Language :: Python :: 3
Classifier: Programming Language :: Python :: 3.3
Classifier: Programming Language :: Python :: 3.4
Classifier: Programming Language :: Python :: 3.5
Classifier: Programming Language :: Python :: 3.6
Classifier: Programming Language :: Python :: 3.7
Classifier: Programming Language :: Python :: 3.8
Classifier: Intended Audience :: Developers
Classifier: Environment :: Plugins
Classifier: License :: OSI Approved :: BSD License
Classifier: Topic :: Internet :: WWW/HTTP
Classifier: Topic :: Utilities
Requires-Dist: httpie (>=1.0.0)
